Metadata-Version: 2.1
Name: find-zx
Version: 0.0.0.1
Summary: p,m,l,t,w,h
Home-page: https://github.com/xvbowen2012
Author: zaixia108
Author-email: xvbowen2012@gmail.com
License: MIT
Platform: UNKNOWN
